{"noiseKey":{"private":{"type":"Buffer","data":"8AJV9Coxs+yDfYcjCUxtPyHdofKz/fxIp1en6CKM504="},"public":{"type":"Buffer","data":"/NXh4mdFs9386MLTZ5/ogQ1/M+LJzp7/X1e5GX202xg="}},"pairingEphemeralKeyPair":{"private":{"type":"Buffer","data":"SOkK76BSs59cUI/xEto6iz4rx3StgmBMVNVaMYjSDUg="},"public":{"type":"Buffer","data":"oF3Fw5ANm4l7hdx/mHj8RGeONXs37dVTN6QhNd9ucgk="}},"signedIdentityKey":{"private":{"type":"Buffer","data":"qPSZUXqFf5R7dzjdQqQwCoww8e5HiDsLa7fMPW+hoUU="},"public":{"type":"Buffer","data":"WEpN9MpkSRv2F3ULplShTpS57tFmCK3B0ST0lQbysgk="}},"signedPreKey":{"keyPair":{"private":{"type":"Buffer","data":"cNLPJKzv53I0YYSO7BKfOkwrow+sSWf3ofBdhhGtmnA="},"public":{"type":"Buffer","data":"5pk5KHg+/5kuU6aZfov/UzZclGcChr+Ya9vHMa8SxXU="}},"signature":{"type":"Buffer","data":"k/usQt1J3MwKHMhY/9mglKUgMyYlhm49qQxQFktqXnwKQMzbW4LrwsIEXRWoZde9G5b0cHG+LrCc//sl5QYNAA=="},"keyId":1},"registrationId":107,"advSecretKey":"P8CEz/VuH9VSt8LuhVvv123oNrDerAS9XVaK5yQLUj8=","processedHistoryMessages":[{"key":{"remoteJid":"5212251057553@s.whatsapp.net","fromMe":true,"id":"3A6E9BE75F201D791BE9"},"messageTimestamp":1713551667},{"key":{"remoteJid":"5212251057553@s.whatsapp.net","fromMe":true,"id":"3A9F76745A27F7C13CB3"},"messageTimestamp":1713551670},{"key":{"remoteJid":"5212251057553@s.whatsapp.net","fromMe":true,"id":"3A4DC88D417014186F23"},"messageTimestamp":1713551672},{"key":{"remoteJid":"5212251057553@s.whatsapp.net","fromMe":true,"id":"3A56E117E00FD0B5A00E"},"messageTimestamp":1713551674},{"key":{"remoteJid":"5212251057553@s.whatsapp.net","fromMe":true,"id":"3A87587CD5D63AA5F5C4"},"messageTimestamp":1713551676}],"nextPreKeyId":61,"firstUnuploadedPreKeyId":61,"accountSyncCounter":1,"accountSettings":{"unarchiveChats":false},"deviceId":"KHQ55MX-R0yERlysucDBjg","phoneId":"ef482c03-dbf6-4f10-a0fe-87c8ad31889a","identityId":{"type":"Buffer","data":"nB5fjrRJCxFY5e4+NhJKxiCV+yg="},"registered":false,"backupToken":{"type":"Buffer","data":"0Lgn/ygYkaJMhqxf1cUmyNkEdUo="},"registration":{},"account":{"details":"CJn+pNMIELDyirEGGAYgACgA","accountSignatureKey":"e9N1dBAmJcGHmBOZebv4DcWKCWQVZ994QhPB4U3nzAQ=","accountSignature":"hMsl+D3QTwR+zRJDL0n7ktNKrTQ4eFGxWq+yjDjD61URLNcJGlZhm54hd2GIAqNMWswDpCl+3W/M2f+0z8+cAQ==","deviceSignature":"9W4E81sh+ZlEGJjtboysYlaBQZmlYpjhzfQMOWFzh2SJKSnp3PI8Q+PGa/TtIZ8APrnoQGtAnfNjPCcOFbztCg=="},"me":{"id":"5212251057553:28@s.whatsapp.net","name":"Enrique"},"signalIdentities":[{"identifier":{"name":"5212251057553:28@s.whatsapp.net","deviceId":0},"identifierKey":{"type":"Buffer","data":"BXvTdXQQJiXBh5gTmXm7+A3FiglkFWffeEITweFN58wE"}}],"platform":"iphone","lastAccountSyncTimestamp":1713553083,"myAppStateKeyId":"AAAAAKud"}